pypkg_recdep/__init__.py
pypkg_recdep/__main__.py
pypkg_recdep/exclude.py
pypkg_recdep/find_pypi_deps.py
pypkg_recdep/internal_server_listing.py
pypkg_recdep/list_ado_content.py
pypkg_recdep/pkg_info.py
pypkg_recdep/pkg_recdep_cmd.py
pypkg_recdep/print_deps.py
pypkg_recdep/py.typed
pypkg_recdep-0.4.dist-info/licenses/LICENSE.txt
pypkg_recdep-0.4.dist-info/METADATA
pypkg_recdep-0.4.dist-info/WHEEL
pypkg_recdep-0.4.dist-info/top_level.txt
pypkg_recdep-0.4.dist-info/RECORD
