Metadata-Version: 2.4
Name: pypkg-recdep
Version: 0.4
Summary: Recursively find dependencies for PyPI packages
Author: Tom Björkholm
Author-email: Tom Björkholm <klausuler_linnet0q@icloud.com>
License-Expression: MIT
Project-URL: Source code, https://bitbucket.org/tom-bjorkholm/pypkg-recdep
Classifier: Programming Language :: Python :: 3
Classifier: Operating System :: OS Independent
Requires-Python: >=3.12
License-File: LICENSE.txt
Requires-Dist: mformat>=0.2.2
Requires-Dist: pypi-simple>=1.8.0
Requires-Dist: packaging>=26.0
Requires-Dist: argcomplete>=3.6.3
Requires-Dist: requests>=2.32.3
Requires-Dist: types-requests>=2.32.4.20250913
Requires-Dist: pip>=25.3
Requires-Dist: setuptools>=80.9.0
Requires-Dist: build>=1.3.0
Requires-Dist: wheel>=0.45.1
Dynamic: author
Dynamic: license-file
Dynamic: requires-dist
Dynamic: requires-python
